nr_theses_metadata/__init__.py
nr_theses_metadata/constants.py
nr_theses_metadata/jsonschemas/__init__.py
nr_theses_metadata/jsonschemas/nr_theses_metadata/__init__.py
nr_theses_metadata/jsonschemas/nr_theses_metadata/nr-theses-metadata-v1.0.0.json
nr_theses_metadata/mapping_includes/__init__.py
nr_theses_metadata/mapping_includes/v7/__init__.py
nr_theses_metadata/mapping_includes/v7/nr-taxonomies-studyfield-v1.0.0.json
nr_theses_metadata/mapping_includes/v7/nr-theses-metadata-v1.0.0.json
nr_theses_metadata/mappings/__init__.py
nr_theses_metadata/mappings/v7/__init__.py
nr_theses_metadata/marshmallow/__init__.py
nr_theses_metadata/marshmallow/json.py
nr_theses_metadata/marshmallow/subschemas.py
nr_theses_metadata/record.py
nr_theses_metadata/search.py
techlib_nr_theses_metadata-1.0.0a13.dist-info/entry_points.txt
techlib_nr_theses_metadata-1.0.0a13.dist-info/WHEEL
techlib_nr_theses_metadata-1.0.0a13.dist-info/METADATA
techlib_nr_theses_metadata-1.0.0a13.dist-info/RECORD
