Metadata-Version: 2.1
Name: techlib-nr-theses-metadata
Version: 1.0.0a13
Summary: Czech National Repository theses data model.
License: MIT
Keywords: Czech,Nation,Repository,Invenio,theses
Author: Daniel Kopecký
Author-email: Daniel.Kopecky@techlib.cz
Requires-Python: >=3.8,<4.0
Classifier: Development Status :: 3 - Alpha
Classifier: Environment :: Web Environment
Classifier: Intended Audience :: Developers
Classifier: License :: OSI Approved :: MIT License
Classifier: Operating System :: OS Independent
Classifier: Programming Language :: Python
Classifier: Programming Language :: Python :: 3
Classifier: Programming Language :: Python :: 3.7
Classifier: Programming Language :: Python :: 3.8
Classifier: Topic :: Internet :: WWW/HTTP :: Dynamic Content
Classifier: Topic :: Software Development :: Libraries :: Python Modules
Requires-Dist: oarepo (>=3.3.59,<4.0.0)
Requires-Dist: techlib-nr-common-metadata (>=3.0.0a48,<4.0.0)
